datadreamer/.env
datadreamer/.gitignore
datadreamer/.secrets.template.env
datadreamer/__cli__.py
datadreamer/__init__.py
datadreamer/__main__.py
datadreamer/_cachable/__init__.py
datadreamer/_cachable/_cachable.py
datadreamer/_cachable/_parallel_cachable.py
datadreamer/_patches/__init__.py
datadreamer/_patches/datasets_reset_state_hack.py
datadreamer/_patches/setfit_import_hack.py
datadreamer/_stubs/.gitkeep
datadreamer/_stubs/datasets/__init__.pyi
datadreamer/datadreamer.py
datadreamer/datasets/__init__.py
datadreamer/datasets/datasets.py
datadreamer/datasets/utils.py
datadreamer/embedders/__init__.py
datadreamer/embedders/embedder.py
datadreamer/embedders/openai_embedder.py
datadreamer/embedders/parallel_embedder.py
datadreamer/embedders/sentence_transformers_embedder.py
datadreamer/embedders/together_embedder.py
datadreamer/errors/__init__.py
datadreamer/errors/steps/__init__.py
datadreamer/errors/steps/step.py
datadreamer/llms/__init__.py
datadreamer/llms/_chat_prompt_templates.py
datadreamer/llms/_litellm.py
datadreamer/llms/_llm_api.py
datadreamer/llms/_tokenizers.py
datadreamer/llms/ai21.py
datadreamer/llms/anthropic.py
datadreamer/llms/bedrock.py
datadreamer/llms/cohere.py
datadreamer/llms/ctransformers.py
datadreamer/llms/google_ai_studio.py
datadreamer/llms/hf_api_endpoint.py
datadreamer/llms/hf_transformers.py
datadreamer/llms/llm.py
datadreamer/llms/mistral_ai.py
datadreamer/llms/openai.py
datadreamer/llms/openai_assistant.py
datadreamer/llms/parallel_llm.py
datadreamer/llms/petals.py
datadreamer/llms/together.py
datadreamer/llms/vertex_ai.py
datadreamer/llms/vllm.py
datadreamer/logging/__init__.py
datadreamer/logging/logger.py
datadreamer/pickling/__init__.py
datadreamer/pickling/pickle.py
datadreamer/project/__init__.py
datadreamer/project/builtin_tasks.py
datadreamer/project/debug.py
datadreamer/project/devices.py
datadreamer/project/environment.py
datadreamer/project/pennnlp.py
datadreamer/project/persistent_storage.py
datadreamer/project/report.py
datadreamer_dev-0.46.0.dist-info/LICENSE.txt
datadreamer_dev-0.46.0.dist-info/METADATA
datadreamer_dev-0.46.0.dist-info/WHEEL
datadreamer_dev-0.46.0.dist-info/RECORD
