Metadata-Version: 2.3
Name: datadreamer.dev
Version: 0.46.0
Summary: Prompt. Generate Synthetic Data. Train & Align Models.
License: MIT
Keywords: python,nlp,machine learning,natural language processing,deep learning,transformers,pytorch,openai,alignment,gpt,nlp library,synthetic data,fine-tuning,synthetic dataset generation,llm,llms,llmops,instruction-tuning
Author: Ajay Patel
Author-email: me@ajayp.app
Maintainer: Ajay Patel
Maintainer-email: me@ajayp.app
Requires-Python: >=3.10,<3.14
Classifier: Development Status :: 5 - Production/Stable
Classifier: Intended Audience :: Developers
Classifier: Intended Audience :: Science/Research
Classifier: License :: OSI Approved :: MIT License
Classifier: Operating System :: MacOS :: MacOS X
Classifier: Operating System :: POSIX :: Linux
Classifier: Programming Language :: Python :: 3
Classifier: Programming Language :: Python :: 3.10
Classifier: Programming Language :: Python :: 3.11
Classifier: Programming Language :: Python :: 3.12
Classifier: Programming Language :: Python :: 3.13
Classifier: Topic :: Scientific/Engineering :: Artificial Intelligence
Requires-Dist: accelerate (>=1.3.0,<2.0.0)
Requires-Dist: bitsandbytes (>=0.45.0,<1.0.0)
Requires-Dist: click (>=8.1.3)
Requires-Dist: ctransformers (>=0.2.27,<1.0.0)
Requires-Dist: datasets (>=3.2.0,<4.0.0)
Requires-Dist: dill (>=0.3.8,<1.0.0)
Requires-Dist: evaluate (>=0.4.3,<1.0.0)
Requires-Dist: faiss-cpu (>=1.9.0.post1,<2.0.0)
Requires-Dist: filelock (>=3.13.1,<4.0.0)
Requires-Dist: huggingface-hub (>=0.27.1,<1.0.0)
Requires-Dist: jsonlines (>=4.0.0,<7.0.0)
Requires-Dist: litellm (==1.57.8)
Requires-Dist: loguru (>=0.7.0,<1.0.0)
Requires-Dist: numpy (>=1.26.4,<2.0.0)
Requires-Dist: openai (>=1.59.6,<2.0.0)
Requires-Dist: optimum (>=1.21.2,<2.0.0)
Requires-Dist: outlines-core (>=0.1.26)
Requires-Dist: pandas (>=1.5.3,<2.0.0)
Requires-Dist: peft (>=0.14.0,<1.0.0)
Requires-Dist: psutil (>=6.1.1)
Requires-Dist: pyro5 (>=5.15)
Requires-Dist: ring (>=0.10.1,<1.0.0)
Requires-Dist: sentence-transformers (>=3.4.0,<4.0.0)
Requires-Dist: setfit (>=1.1.1,<2.0.0)
Requires-Dist: sortedcontainers (>=2.4.0,<3.0.0)
Requires-Dist: sqlitedict (>=2.1.0,<3.0.0)
Requires-Dist: tenacity (>=9.0.0)
Requires-Dist: tiktoken (>=0.7.0,<1.0.0)
Requires-Dist: torch (>=2.5.1,<3.0.0)
Requires-Dist: transformers (>=4.48.1,<4.50.0)
Requires-Dist: trl (==0.9.6)
Project-URL: Documentation, https://datadreamer.dev/docs/
Project-URL: Homepage, https://datadreamer.dev/
Project-URL: Repository, https://github.com/datadreamer-dev/DataDreamer
